creds/__init__.py
creds/cli.py
creds/cred.py
creds/defaults.py
creds/main.py
creds/util.py
aws_creds-2.0.1.dist-info/LICENSE
aws_creds-2.0.1.dist-info/METADATA
aws_creds-2.0.1.dist-info/WHEEL
aws_creds-2.0.1.dist-info/entry_points.txt
aws_creds-2.0.1.dist-info/top_level.txt
aws_creds-2.0.1.dist-info/RECORD
