Metadata-Version: 2.1
Name: aws-creds
Version: 2.0.1
Summary: Easily switch between AWS Credential profiles.
Home-page: https://github.com/HammoTime/aws-creds
Author: Adam Hammond
Author-email: adam@hammo.io
License: UNKNOWN
Platform: UNKNOWN
Classifier: Development Status :: 5 - Production/Stable
Classifier: Environment :: Console
Classifier: Programming Language :: Python :: 3
Classifier: Programming Language :: Python :: 3.7
Classifier: License :: OSI Approved :: MIT License
Classifier: Operating System :: OS Independent
Classifier: Natural Language :: English
Classifier: Topic :: System :: Systems Administration
Requires-Dist: boto3
Requires-Dist: click
